geotaichi/__init__.py
src/__init__.py
src/dem/BaseKernel.py
src/dem/BaseStruct.py
src/dem/ContactManager.py
src/dem/DEMBase.py
src/dem/GenerateManager.py
src/dem/PostPlot.py
src/dem/Recorder.py
src/dem/SceneManager.py
src/dem/Simulation.py
src/dem/__init__.py
src/dem/mainDEM.py
src/dem/contact/ContactKernel.py
src/dem/contact/ContactModelBase.py
src/dem/contact/HertzMindlin.py
src/dem/contact/JiangRolling.py
src/dem/contact/Linear.py
src/dem/contact/LinearBond.py
src/dem/contact/LinearRolling.py
src/dem/contact/__init__.py
src/dem/engines/ElementTest.py
src/dem/engines/EngineKernel.py
src/dem/engines/ExplicitEngine.py
src/dem/engines/__init__.py
src/dem/generator/BodyGenerator.py
src/dem/generator/BrustNeighbor.py
src/dem/generator/ClumpTemplate.py
src/dem/generator/InsertionKernel.py
src/dem/generator/LinkedCellNeighbor.py
src/dem/generator/LoadFromFile.py
src/dem/generator/WallGenerator.py
src/dem/generator/__init__.py
src/dem/neighbor/BrustSearch.py
src/dem/neighbor/LinkedCell.py
src/dem/neighbor/NeighborBase.py
src/dem/neighbor/__init__.py
src/dem/neighbor/neighbor_kernel.py
src/mpdem/ContactManager.py
src/mpdem/DEMPMBase.py
src/mpdem/Engine.py
src/mpdem/MixtureGenerate.py
src/mpdem/Recorder.py
src/mpdem/Simulation.py
src/mpdem/__init__.py
src/mpdem/mainDEMPM.py
src/mpdem/contact/ContactKernel.py
src/mpdem/contact/ContactModelBase.py
src/mpdem/contact/HertzMindlin.py
src/mpdem/contact/Linear.py
src/mpdem/contact/LinearBond.py
src/mpdem/contact/MultiLinkedCell.py
src/mpdem/contact/ParticleFluid.py
src/mpdem/contact/__init__.py
src/mpm/BaseKernel.py
src/mpm/BaseStruct.py
src/mpm/GenerateManager.py
src/mpm/MPMBase.py
src/mpm/MaterialManager.py
src/mpm/PostPlot.py
src/mpm/Recorder.py
src/mpm/SceneManager.py
src/mpm/Simulation.py
src/mpm/SpatialHashGrid.py
src/mpm/__init__.py
src/mpm/mainMPM.py
src/mpm/boundaries/BoundaryCore.py
src/mpm/boundaries/BoundaryStrcut.py
src/mpm/boundaries/__init__.py
src/mpm/elements/ElementBase.py
geotaichi-0.2.6.dist-info/LICENSE
geotaichi-0.2.6.dist-info/METADATA
geotaichi-0.2.6.dist-info/WHEEL
geotaichi-0.2.6.dist-info/top_level.txt
geotaichi-0.2.6.dist-info/RECORD
