Metadata-Version: 2.1
Name: geotaichi
Version: 0.2.6
Summary: A Taichi-powered high-performance numerical simulator for multiscale geophysical problems
Home-page: https://github.com/Yihao-Shi/GeoTaichi
Author: Shi-YiHao
Author-email: syh-1999@outlook.com
Classifier: Programming Language :: Python :: 3.8
Classifier: Programming Language :: Python :: 3.9
Classifier: Programming Language :: Python :: 3.10
Classifier: License :: OSI Approved :: GNU Affero General Public License v3
Classifier: Development Status :: 3 - Alpha
Requires-Python: >=3.8,<=3.11
License-File: LICENSE
Requires-Dist: taichi ==1.6.0
Requires-Dist: numpy ==1.23.5
Requires-Dist: psutil
Requires-Dist: pynvml
Requires-Dist: scipy ==1.10.1
Requires-Dist: trimesh ==3.20.1
Requires-Dist: shapely ==1.8.0
Requires-Dist: rtree
